{
    "attributes": {
        "description": "Entry panel showing overall metrics.",
        "hits": 0,
        "kibanaSavedObjectMeta": {
            "searchSourceJSON": "{\"query\":{\"language\":\"lucene\",\"query\":\"\"},\"filter\":[{\"$state\":{\"store\":\"appState\"},\"meta\":{\"alias\":\"Bots\",\"disabled\":false,\"index\":\"git_enrich\",\"key\":\"author_bot\",\"negate\":true,\"params\":{\"query\":true,\"type\":\"phrase\"},\"type\":\"phrase\",\"value\":\"true\"},\"query\":{\"match\":{\"author_bot\":{\"query\":true,\"type\":\"phrase\"}}}}]}"
        },
        "optionsJSON": "{\"darkTheme\":false,\"hidePanelTitles\":false,\"useMargins\":true}",
        "panelsJSON": "[{\"embeddableConfig\":{},\"gridData\":{\"h\":18,\"i\":\"2\",\"w\":29,\"x\":0,\"y\":22},\"id\":\"0fddebf0-14e1-11e9-8aac-ef7fd4d8cbad\",\"panelIndex\":\"2\",\"title\":\"Contributions\",\"type\":\"visualization\",\"version\":\"6.7.1\"},{\"embeddableConfig\":{},\"gridData\":{\"h\":18,\"i\":\"3\",\"w\":29,\"x\":0,\"y\":4},\"id\":\"8cfe1960-18de-11e9-ba47-d5cbef43f8d3\",\"panelIndex\":\"3\",\"title\":\"Contributors Growth and Difference to the Average\",\"type\":\"visualization\",\"version\":\"6.7.1\"},{\"embeddableConfig\":{},\"gridData\":{\"h\":18,\"i\":\"4\",\"w\":19,\"x\":29,\"y\":40},\"id\":\"b92683a0-a2ff-11e9-ac51-1516462fb85e\",\"panelIndex\":\"4\",\"title\":\"\",\"type\":\"visualization\",\"version\":\"6.7.1\"},{\"embeddableConfig\":{},\"gridData\":{\"h\":18,\"i\":\"5\",\"w\":19,\"x\":29,\"y\":4},\"id\":\"141a5bb0-a300-11e9-ac51-1516462fb85e\",\"panelIndex\":\"5\",\"title\":\"\",\"type\":\"visualization\",\"version\":\"6.7.1\"},{\"embeddableConfig\":{},\"gridData\":{\"h\":7,\"i\":\"6\",\"w\":48,\"x\":0,\"y\":74},\"id\":\"26024040-a300-11e9-ac51-1516462fb85e\",\"panelIndex\":\"6\",\"title\":\"\",\"type\":\"visualization\",\"version\":\"6.7.1\"},{\"embeddableConfig\":{},\"gridData\":{\"h\":18,\"i\":\"7\",\"w\":19,\"x\":29,\"y\":22},\"id\":\"a4b825d0-a300-11e9-ac51-1516462fb85e\",\"panelIndex\":\"7\",\"title\":\"\",\"type\":\"visualization\",\"version\":\"6.7.1\"},{\"embeddableConfig\":{},\"gridData\":{\"h\":18,\"i\":\"8\",\"w\":29,\"x\":0,\"y\":40},\"id\":\"d61c9a70-a30a-11e9-ac51-1516462fb85e\",\"panelIndex\":\"8\",\"title\":\"Timing\",\"type\":\"visualization\",\"version\":\"6.7.1\"},{\"embeddableConfig\":{},\"gridData\":{\"h\":4,\"i\":\"9\",\"w\":48,\"x\":0,\"y\":0},\"id\":\"d69af2a0-14f6-11e9-8aac-ef7fd4d8cbad\",\"panelIndex\":\"9\",\"title\":\"\",\"type\":\"visualization\",\"version\":\"6.7.1\"},{\"embeddableConfig\":{},\"gridData\":{\"h\":16,\"i\":\"10\",\"w\":19,\"x\":29,\"y\":58},\"id\":\"b464fd20-c810-11e9-b0eb-85688658d306\",\"panelIndex\":\"10\",\"title\":\"\",\"type\":\"visualization\",\"version\":\"6.7.1\"},{\"embeddableConfig\":{\"vis\":{\"legendOpen\":true}},\"gridData\":{\"h\":16,\"i\":\"11\",\"w\":29,\"x\":0,\"y\":58},\"id\":\"meetup_events_evolutionary\",\"panelIndex\":\"11\",\"title\":\"Meetup Events\",\"type\":\"visualization\",\"version\":\"6.7.1\"}]",
        "refreshInterval": {
            "pause": true,
            "value": 0
        },
        "timeFrom": "now-2y",
        "timeRestore": true,
        "timeTo": "now",
        "title": "Metrics Overview",
        "version": 1
    },
    "id": "8c34bc50-a2fe-11e9-ac51-1516462fb85e",
    "type": "dashboard",
    "updated_at": "2019-08-29T12:04:27.841Z",
    "version": "WzExOCwxXQ=="
}